jcloudai/__init__.py
jcloudai/__version__.py
jcloudai/agent/__init__.py
jcloudai/agent/base.py
jcloudai/agent/state.py
jcloudai/chat接口SQL校验改造实现方案.md
jcloudai/chat接口逻辑改造.md
jcloudai/chat接口逻辑梳理.md
jcloudai/cli/__init__.py
jcloudai/cli/main.py
jcloudai/config.py
jcloudai/constants.py
jcloudai/core/code_execution/__init__.py
jcloudai/core/code_execution/code_executor.py
jcloudai/core/code_execution/environment.py
jcloudai/core/code_generation/__init__.py
jcloudai/core/code_generation/base.py
jcloudai/core/code_generation/code_cleaning.py
jcloudai/core/code_generation/code_validation.py
jcloudai/core/code_generation/sql_validator.py
jcloudai/core/prompts/__init__.py
jcloudai/core/prompts/base.py
jcloudai/core/prompts/correct_execute_sql_query_usage_error_prompt.py
jcloudai/core/prompts/correct_output_type_error_prompt.py
jcloudai/core/prompts/generate_python_code_with_sql.py
jcloudai/core/prompts/generate_system_message.py
jcloudai/core/prompts/templates/correct_execute_sql_query_usage_error_prompt.tmpl
jcloudai/core/prompts/templates/correct_output_type_error_prompt.tmpl
jcloudai/core/prompts/templates/generate_python_code_with_sql.tmpl
jcloudai/core/prompts/templates/generate_system_message.tmpl
jcloudai/core/prompts/templates/shared/dataframe.tmpl
jcloudai/core/prompts/templates/shared/output_type_template.tmpl
jcloudai/core/prompts/templates/shared/vectordb_docs.tmpl
jcloudai/core/prompts/templates/validate_sql_prompt.tmpl
jcloudai/core/prompts/validate_sql_prompt.py
jcloudai/core/response/__init__.py
jcloudai/core/response/base.py
jcloudai/core/response/chart.py
jcloudai/core/response/dataframe.py
jcloudai/core/response/error.py
jcloudai/core/response/number.py
jcloudai/core/response/parser.py
jcloudai/core/response/string.py
jcloudai/core/user_query.py
jcloudai/data_loader/duck_db_connection_manager.py
jcloudai/data_loader/loader.py
jcloudai/data_loader/local_loader.py
jcloudai/data_loader/semantic_layer_schema.py
jcloudai/data_loader/sql_loader.py
jcloudai-1.0.18.dist-info/METADATA
jcloudai-1.0.18.dist-info/WHEEL
jcloudai-1.0.18.dist-info/entry_points.txt
jcloudai-1.0.18.dist-info/licenses/LICENSE
jcloudai-1.0.18.dist-info/RECORD
