Metadata-Version: 2.4
Name: jcloudai
Version: 1.0.18
Summary: Chat with your database (SQL, CSV, pandas, mongodb, noSQL, etc). PandasAI makes data analysis conversational using LLMs (GPT 3.5 / 4, Anthropic, VertexAI) and RAG.
License: MIT
License-File: LICENSE
Author: Yun GU
Requires-Python: >=3.8,<3.12
Classifier: License :: OSI Approved :: MIT License
Classifier: Programming Language :: Python :: 3
Classifier: Programming Language :: Python :: 3.8
Classifier: Programming Language :: Python :: 3.9
Classifier: Programming Language :: Python :: 3.10
Classifier: Programming Language :: Python :: 3.11
Requires-Dist: astor (>=0.8.1,<0.9.0)
Requires-Dist: duckdb (>=1.0.0,<2.0.0)
Requires-Dist: jinja2 (>=3.1.3,<4.0.0)
Requires-Dist: matplotlib (>=3.7.1,<3.8)
Requires-Dist: numpy (>=1.17,<2.0)
Requires-Dist: openpyxl (>=3.1.5,<4.0.0)
Requires-Dist: pandas (>=2.0.3,<3.0.0)
Requires-Dist: pillow (>=10.1.0,<11.0.0)
Requires-Dist: pyarrow (>=14.0.1,<15.0.0)
Requires-Dist: pydantic (>=2.6.4,<3.0.0)
Requires-Dist: python-dotenv (>=1.0.0,<2.0.0)
Requires-Dist: pyyaml (>=6.0.2,<7.0.0)
Requires-Dist: requests (>=2.31.0,<3.0.0)
Requires-Dist: scipy (==1.10.1)
Requires-Dist: seaborn (>=0.12.2,<0.13.0)
Requires-Dist: sqlglot (>=25.0.3,<26.0.0)
Project-URL: Documentation, https://docs.getpanda.ai/
Project-URL: Repository, https://github.com/sinaptik-ai/pandas-ai
